LICENSE
MANIFEST.in
README.rst
setup.cfg
setup.py
tavern/__init__.py
tavern/core.py
tavern/entry.py
tavern/mqtt.py
tavern/plugins.py
tavern/printer.py
tavern/request/__init__.py
tavern/request/base.py
tavern/request/mqtt.py
tavern/request/rest.py
tavern/response/__init__.py
tavern/response/base.py
tavern/response/mqtt.py
tavern/response/rest.py
tavern/schemas/__init__.py
tavern/schemas/extensions.py
tavern/schemas/files.py
tavern/schemas/tests.schema.yaml
tavern/testutils/__init__.py
tavern/testutils/helpers.py
tavern/testutils/pytesthook.py
tavern/util/__init__.py
tavern/util/delay.py
tavern/util/dict_util.py
tavern/util/exceptions.py
tavern/util/general.py
tavern/util/loader.py
tavern/util/python_2_util.py
tavern_extended.egg-info/PKG-INFO
tavern_extended.egg-info/SOURCES.txt
tavern_extended.egg-info/dependency_links.txt
tavern_extended.egg-info/entry_points.txt
tavern_extended.egg-info/requires.txt
tavern_extended.egg-info/top_level.txt