Metadata-Version: 2.1
Name: tavern-extended
Version: 0.9.1
Summary: Simple testing of RESTful APIs
Home-page: https://taverntesting.github.io/
Author: Michael Boulton
Author-email: boulton@zoetrope.io
License: MIT
Keywords: testing,pytest
Platform: UNKNOWN
Classifier: Development Status :: 5 - Production/Stable
Classifier: Intended Audience :: Developers
Classifier: Framework :: Pytest
Classifier: Programming Language :: Python :: 2
Classifier: Programming Language :: Python :: 2.7
Classifier: Programming Language :: Python :: 3
Classifier: Programming Language :: Python :: 3.4
Classifier: Programming Language :: Python :: 3.5
Classifier: Programming Language :: Python :: 3.6
Classifier: Topic :: Utilities
Classifier: Topic :: Software Development :: Testing
Classifier: License :: OSI Approved :: MIT License
Provides-Extra: mqtt
Provides-Extra: pytest
